{
  "hosting": {
    "amplifyhosting": {
      "service": "amplifyhosting",
      "providerPlugin": "awscloudformation",
      "type": "manual"
    }
  },
  "auth": {
    "chatappbe27ed0b": {
      "service": "Cognito",
      "providerPlugin": "awscloudformation",
      "dependsOn": [],
      "customAuth": false
    }
  },
  "api": {
    "chatapp": {
      "service": "AppSync",
      "providerPlugin": "awscloudformation",
      "output": {
        "authConfig": {
          "defaultAuthentication": {
            "authenticationType": "AMAZON_COGNITO_USER_POOLS",
            "userPoolConfig": {
              "userPoolId": "authchatappbe27ed0b"
            }
          },
          "additionalAuthenticationProviders": []
        }
      }
    }
  },
  "storage": {
    "bucket": {
      "service": "S3",
      "providerPlugin": "awscloudformation"
    }
  }
}